{
  "agreements": [
    {
      "id": "3",
      "user_id": "1",
      "file_path": null,
      "performer_name": "asdas",
      "id_code_or_personal_number": "asdasd",
      "legal_or_actual_address": "dasdasdasd",
      "bank_account_details": "gasdasd",
      "representative_name": "asdasd",
      "contact_info": "fgasdasdasdasd",
      "contract_start_period": "2024-09-20",
      "service_description": "asdasd",
      "service_price": "123123.00",
      "payment_terms": "fdsfas",
      "service_location": "sadas",
      "contract_duration": "2024-09-14",
      "contract_responsible_person": "d1w31d",
      "created_at": "2024-09-20 12:45:31",
      "updated_at": "2024-10-01 19:39:25",
      "status": "approved",
      "limit_type": null,
      "limit_amount": null,
      "consignment_term": null,
      "place_time_of_delivery": null,
      "product_cost": null,
      "payment_term": null,
      "means_of_securing_obligation": null,
      "notary_agreement": "0",
      "initiator_name_signature": null,
      "manager_name_signature": null
    }
  ],
  "approval_steps": [
    {
      "id": "155",
      "model_id": "100",
      "model_type": "App\\Models\\Vocation",
      "step": "1",
      "user_id": null,
      "status": "pending",
      "comment": null,
      "approve_at": null,
      "created_at": "2024-11-21 08:50:45",
      "updated_at": "2024-11-21 08:50:45",
      "department_id": "5",
      "is_final_step": "0"
    }
  ],
  "branches": [],
  "business_trips": [
    {
      "id": "18",
      "user_id": "1",
      "place_of_trip": "ragac",
      "business_trip_basis": null,
      "purpose_of_trip": "asda",
      "description": null,
      "business_trip_arrangement": null,
      "start_date": "2024-11-06",
      "end_date": "2024-11-27",
      "status": "rejected",
      "expected_result_business_trip": null,
      "expense_vocation": "14124",
      "expense_transport": "12412",
      "expense_living": "23412",
      "total_expense": "12414",
      "expense_meal": "123412",
      "trip_type": "international",
      "actual_result": null,
      "created_at": "2024-11-21 07:48:22",
      "updated_at": "2024-11-21 07:58:37",
      "subtitle_user_name": "mandarini",
      "subtitle_user_sur_name": "mandarini",
      "subtitle_user_position": null,
      "comment": "asddsa",
      "reviewed_at": "2024-11-21 07:58:37",
      "reviewed_by": "1"
    }
  ],
  "chats": [],
  "chat_members": [],
  "chat_messages": [],
  "comments": [],
  "contact_marketing": [
    {
      "id": "9",
      "name": "ნიკა",
      "surname": "ყაულაშვილი",
      "id_number": "31001003331",
      "mobile_number": "5774456212",
      "email": "n.kaulashvili@gorgia.ge",
      "created_at": "2024-10-28 14:23:02",
      "updated_at": "2024-10-28 14:23:02"
    }
  ],
  "dailies": [
    {
      "id": "107",
      "date": "2024-11-06",
      "name": "TEA",
      "description": "TEA",
      "user_id": "1",
      "department_id": "22",
      "created_at": "2024-11-06 14:18:13",
      "updated_at": "2024-11-06 14:18:13",
      "attachment": null,
      "link": null
    }
  ],
  "daily_comments": [
    {
      "id": "322",
      "daily_id": "106",
      "department_id": null,
      "user_id": "1",
      "parent_id": "321",
      "comment": "adwqweqwr",
      "created_at": "2024-11-20 13:46:17",
      "updated_at": "2024-11-20 13:46:17"
    }
  ],
  "departments": [
    {
      "id": "41",
      "name": "სტანდარტები",
      "type": "department",
      "description": "სტანდარტები",
      "status": "active",
      "user_id": "15",
      "created_at": "2024-10-02 08:52:15",
      "updated_at": "2024-10-02 08:52:29"
    }
  ],
  "discounts": [
    {
      "id": "1",
      "user_id": "3",
      "realization_code": "dasd",
      "sale_type": null,
      "created_at": "2024-07-26 15:14:48",
      "updated_at": "2024-07-26 15:14:48"
    }
  ],
  "failed_jobs": [],
  "groups": [],
  "group_users": [],
  "hr_documents": [
    {
      "id": "90",
      "user_id": "3",
      "name": "გამოსაცდელი ვადით უხელფასო",
      "status": "approved",
      "created_at": "2024-11-25 08:50:36",
      "updated_at": "2024-11-25 08:50:36",
      "salary": null,
      "salary_text": null,
      "comment": null,
      "purpose": null
    }
  ],
  "internal_purchases": [
    {
      "id": "41",
      "user_id": "1",
      "department_id": "36",
      "department_purchase_id": "5",
      "objective": "Test",
      "reason": "Test",
      "deadline": "2024-11-30",
      "short_period_reason": "Test",
      "requested_procurement_object_exceed": null,
      "stock_purpose": "Test",
      "delivery_address": "Test",
      "brand_model": "Test",
      "alternative": "Test",
      "competitive_price": null,
      "planned_next_month": "Test",
      "who_pay_amount": "Test",
      "name_surname_of_employee": "Test",
      "status": "pending",
      "created_at": "2024-11-21 06:39:13",
      "updated_at": "2024-11-21 06:39:13",
      "comment": null,
      "reviewed_at": "2024-11-21 07:04:47",
      "reviewed_by": "1"
    }
  ],
  "invoices": [
    {
      "id": "7",
      "department": "30",
      "invoice_file": "invoices/O2DqU5c3jfOSEBb89qvaYrVzJ8fi9CMupnbxHBUA.pdf",
      "status": "completed",
      "comments": "asddsa",
      "created_at": "2024-11-20 13:35:48",
      "updated_at": "2024-11-20 13:35:48"
    }
  ],
  "leads": [
    {
      "id": "10",
      "first_name": "Sopho",
      "last_name": "sopho",
      "request": "test",
      "responsible_person": "test",
      "status": "Active",
      "comment": "Test",
      "created_at": "2024-09-24 08:27:38",
      "updated_at": "2024-10-01 06:24:01"
    }
  ],
  "lead_request_comments": [],
  "meetings": [
    {
      "id": "6",
      "title": "zzzzzzz",
      "start_time": "2024-11-08 03:00:00",
      "end_time": "2024-11-08 05:00:00",
      "reason": "zzzzz",
      "comments": "zzzzzzzzz",
      "created_by": "1",
      "created_at": "2024-11-22 05:45:38",
      "updated_at": "2024-11-22 05:45:38",
      "deleted_at": null
    }
  ],
  "meeting_users": [
    {
      "id": "7",
      "meeting_id": "6",
      "user_id": "14",
      "status": "pending",
      "created_at": "2024-11-22 05:45:38",
      "updated_at": "2024-11-22 05:45:38"
    }
  ],
  "messages": [
    {
      "id": "26",
      "sender_id": "1",
      "receiver_id": "1",
      "group_id": null,
      "message": "asddsa",
      "created_at": "2024-11-19 10:05:47",
      "updated_at": "2024-11-19 10:05:47"
    }
  ],
  "migrations": [
    {
      "id": "65",
      "migration": "2024_11_22_102936_remove_field_vip_lead_request",
      "batch": "39"
    }
  ],
  "nearest_events": [
    {
      "id": "2",
      "user_id": "3",
      "title": "dasd",
      "date": "2024-07-26",
      "priority": "0",
      "created_at": "2024-07-26 15:16:58",
      "updated_at": "2024-07-26 15:16:58",
      "time": null,
      "description": null
    }
  ],
  "notes": [
    {
      "id": "34",
      "user_id": "1",
      "content": "<p>dhdfhfgh</p>",
      "created_at": "2024-11-21 06:43:49",
      "updated_at": "2024-11-21 06:43:49",
      "title": "xjfgjf"
    }
  ],
  "notifications": [
    {
      "id": "1240",
      "user_id": "52",
      "replied_comment_id": null,
      "comment_id": "315",
      "message": "CRM added a new comment on \"\".",
      "is_read": "0",
      "created_at": "2024-10-29 13:02:24",
      "updated_at": "2024-10-29 13:02:24"
    }
  ],
  "password_reset_tokens": [],
  "personal_access_tokens": [
    {
      "id": "3",
      "tokenable_type": "App\\Models\\User",
      "tokenable_id": "2",
      "name": "auth_token",
      "token": "d77bef046fb610bf85c7104f46bcd4e5d335736ee65317eb7ecbe032288c94ae",
      "abilities": ["*"],
      "last_used_at": null,
      "expires_at": null,
      "created_at": "2024-06-26 08:57:56",
      "updated_at": "2024-06-26 08:57:56"
    }
  ],
  "purchase_requirements": [],
  "tasks": [
    {
      "id": "17",
      "user_id": null,
      "task_title": "ელ-ფოსტის პრობლემა",
      "description": "asdasd",
      "assigned_to": "1",
      "due_date": "2024-09-20",
      "priority": "High",
      "status": "Completed",
      "ip_address": "192.168.1.1",
      "created_at": "2024-09-20 06:39:21",
      "updated_at": "2024-10-01 19:46:19",
      "start_time": "2024-10-01 19:46:09",
      "end_time": "2024-10-01 19:46:19",
      "execution_time": "0.00",
      "assignment_reminder_sent": "0"
    }
  ],
  "task_comments": [
    {
      "id": "19",
      "task_id": "32",
      "user_id": "23",
      "comment_text": "sadasd",
      "created_at": "2024-10-02 11:41:19",
      "updated_at": "2024-10-02 11:41:19"
    }
  ],
  "users": [
    {
      "id": "1",
      "type": "admin",
      "position": "admin",
      "department_id": "36",
      "location": "admin",
      "working_start_date": "2024-06-13",
      "date_of_birth": "2024-06-13",
      "name": "მერაბი",
      "surname": "ბაუჟაძე",
      "mobile_number": "591734747",
      "email": "admin@gorgia.ge",
      "profile_image": null,
      "email_verified_at": null,
      "password": "$2y$12$syGDUrS1tfNRHONO54Bc3OwTcxBZq9GlywT8kZoyKQMiVLb66daPm",
      "password_reset_token": null,
      "status": "active",
      "remember_token": null,
      "created_at": "2024-06-25 18:44:36",
      "updated_at": "2024-11-06 14:15:39",
      "salary": null,
      "salary_text": null,
      "work_start_date": "2024-01-01",
      "document_id": null,
      "id_number": "61004065900"
    }
  ],
  "vip_leads": [
    {
      "id": "18",
      "first_name": "asddsa",
      "last_name": "asddsa",
      "created_at": "2024-11-25 08:27:37",
      "updated_at": "2024-11-25 08:27:37",
      "phone": "551002206"
    }
  ],
  "vip_lead_requests": [
    {
      "id": "1",
      "name": "პირველი სატესტო მოთხოვნა",
      "request_status": "pending",
      "creation_date": "2024-11-25 14:44:30",
      "vip_lead_id": "18",
      "created_at": "2024-11-25 12:35:35",
      "updated_at": null
    }
  ],
  "visitors_traffic": [
    {
      "id": "1",
      "date": "2024-09-11",
      "office": "დიდუბის ფილიალი",
      "visitors_count": "1001",
      "created_at": "2024-09-11 09:59:45",
      "updated_at": "2024-09-11 10:40:52"
    }
  ],
  "vocations": [
    {
      "id": "1",
      "user_id": "1",
      "type_of_vocation": null,
      "start_date": "2024-06-27",
      "end_date": "2024-07-05",
      "status": "pending",
      "reason": "no need",
      "monday": "no",
      "tuesday": "no",
      "wednesday": "no",
      "thursday": "no",
      "friday": "no",
      "saturday": "no",
      "sunday": "no",
      "created_at": "2024-06-26 07:40:39",
      "updated_at": "2024-06-26 07:40:39",
      "department_approval": "pending",
      "hr_approval": "pending",
      "department_approval_at": null,
      "hr_approval_at": null,
      "reviewed_by": "1",
      "reviewed_at": "2024-11-21 07:32:22",
      "comment": null,
      "duration": "0"
    }
  ]
}
